{"basics":{"name":"Tianlun ZHOU","label":"","image":"","email":"tianlunzhou.comm@gmail.com","phone":"","url":"https://talentchow.github.io/","summary":"A Ph.D. student in Communication.","location":{"address":"808 CVA Building","postalCode":"","city":"Hong Kong SAR","countryCode":"CHN","region":"Hong Kong SAR"},"profiles":[{"network":"","username":"","url":""}]},"education":[{"institution":"Hong Kong Baptist University","location":"Hong Kong SAR, China","url":"https://www.hkbu.edu.hk/","area":"AI and Digital Media","studyType":"M.Sc.","startDate":"2021-09","endDate":"2022-11","score":""},{"institution":"Hong Kong Baptist University","location":"Hong Kong SAR, China","url":"https://www.hkbu.edu.hk/","area":"Ethics and Public Affairs","studyType":"M.A.","startDate":"2019-09","endDate":"2020-11","score":""}],"awards":[{"title":"Nobel Prize in Physics","date":"1921-11-01","awarder":"Royal Swedish Academy of Sciences","url":"https://www.nobelprize.org/prizes/physics/1921/einstein/biographical/","summary":"The Nobel Prizes are five separate prizes that, according to Alfred Nobel's will of 1895, are awarded to 'those who, during the preceding year, have conferred the greatest benefit to humankind.'"}],"skills":[{"name":"Data Analysis","level":"","icon":"fa-solid fa-hashtag","keywords":["SPSS","AMOS","Gephi","SQLite","Mplus"]},{"name":"Office","level":"","icon":"fa-solid fa-hashtag","keywords":["Word","Excel","PowerPoint","Visio"]},{"name":"Multimedia","level":"","icon":"fa-solid fa-hashtag","keywords":["Adobe Premiere","Photoshop","Illustrator","Edius"]},{"name":"Programming","level":"","icon":"fa-solid fa-hashtag","keywords":["Python","R"]}],"languages":[{"language":"Mandarin","fluency":"Native speaker","icon":""},{"language":"English","fluency":"Fluent","icon":""}],"interests":[{"name":"Communication","icon":"fa-solid fa-tag","keywords":["Digital Journalism","Political Communication","Human-computer Interaction","Information & Communication Technology","Computational Social Science"]}]}